unionai_reuse-0.1.10.data/scripts/unionai-actor-bridge
unionai_actor_executor/_lib.abi3.so
unionai_actor_executor/_version.py
unionai_actor_executor/_module_mgmt.py
unionai_actor_executor/__init__.py
unionai_reuse-0.1.10.dist-info/WHEEL
unionai_reuse-0.1.10.dist-info/entry_points.txt
unionai_reuse-0.1.10.dist-info/top_level.txt
unionai_reuse-0.1.10.dist-info/METADATA
unionai_reuse-0.1.10.dist-info/RECORD
unionai_reuse-0.1.10.dist-info/licenses/licenses/APL.txt
unionai_reuse-0.1.10.dist-info/licenses/licenses/BSL.txt
