Metadata-Version: 2.4
Name: unionai-reuse
Version: 0.1.10
Summary: Enables actor v2
Author-email: unionai <info@union.ai>
Classifier: Intended Audience :: Science/Research
Classifier: Intended Audience :: Developers
Classifier: License :: Other/Proprietary License
Classifier: Programming Language :: Python :: 3
Classifier: Topic :: Scientific/Engineering
Classifier: Topic :: Scientific/Engineering :: Artificial Intelligence
Classifier: Topic :: Software Development
Classifier: Topic :: Software Development :: Libraries
Classifier: Topic :: Software Development :: Libraries :: Python Modules
Requires-Python: >=3.10
License-File: licenses/APL.txt
License-File: licenses/BSL.txt
Requires-Dist: flyte<2.1.0,>=2.0.0b23
Dynamic: license-file
